pypillar/__init__.py
pypillar/common.py
pypillar/static/css/adminlte.css
pypillar/static/css/adminlte.css.map
pypillar/static/css/adminlte.min.css
pypillar/static/css/adminlte.min.css.map
pypillar/static/css/custom.css
pypillar/static/css/fonts.css
pypillar/static/fonts/6xK1dSBYKcSV-LCoeQqfX1RYOo3qPZ7jsDJT9g.woff2
pypillar/static/fonts/6xK1dSBYKcSV-LCoeQqfX1RYOo3qPZ7ksDJT9g.woff2
pypillar/static/fonts/6xK1dSBYKcSV-LCoeQqfX1RYOo3qPZ7nsDI.woff2
pypillar/static/fonts/6xK1dSBYKcSV-LCoeQqfX1RYOo3qPZ7osDJT9g.woff2
pypillar/static/fonts/6xK1dSBYKcSV-LCoeQqfX1RYOo3qPZ7psDJT9g.woff2
pypillar/static/fonts/6xK1dSBYKcSV-LCoeQqfX1RYOo3qPZ7qsDJT9g.woff2
pypillar/static/fonts/6xK1dSBYKcSV-LCoeQqfX1RYOo3qPZ7rsDJT9g.woff2
pypillar/static/fonts/6xK3dSBYKcSV-LCoeQqfX1RYOo3qN67lqDY.woff2
pypillar/static/fonts/6xK3dSBYKcSV-LCoeQqfX1RYOo3qNK7lqDY.woff2
pypillar/static/fonts/6xK3dSBYKcSV-LCoeQqfX1RYOo3qNa7lqDY.woff2
pypillar/static/fonts/6xK3dSBYKcSV-LCoeQqfX1RYOo3qNq7lqDY.woff2
pypillar/static/fonts/6xK3dSBYKcSV-LCoeQqfX1RYOo3qO67lqDY.woff2
pypillar/static/fonts/6xK3dSBYKcSV-LCoeQqfX1RYOo3qOK7l.woff2
pypillar/static/fonts/6xK3dSBYKcSV-LCoeQqfX1RYOo3qPK7lqDY.woff2
pypillar/static/fonts/6xKydSBYKcSV-LCoeQqfX1RYOo3ig4vwkxduz8A.woff2
pypillar/static/fonts/6xKydSBYKcSV-LCoeQqfX1RYOo3ig4vwlBduz8A.woff2
pypillar/static/fonts/6xKydSBYKcSV-LCoeQqfX1RYOo3ig4vwlxdu.woff2
pypillar/static/fonts/6xKydSBYKcSV-LCoeQqfX1RYOo3ig4vwmBduz8A.woff2
pypillar/static/fonts/6xKydSBYKcSV-LCoeQqfX1RYOo3ig4vwmRduz8A.woff2
pypillar/static/fonts/6xKydSBYKcSV-LCoeQqfX1RYOo3ig4vwmhduz8A.woff2
pypillar/static/fonts/6xKydSBYKcSV-LCoeQqfX1RYOo3ig4vwmxduz8A.woff2
pypillar/static/fonts/6xKydSBYKcSV-LCoeQqfX1RYOo3ik4zwkxduz8A.woff2
pypillar/static/fonts/6xKydSBYKcSV-LCoeQqfX1RYOo3ik4zwlBduz8A.woff2
pypillar/static/fonts/6xKydSBYKcSV-LCoeQqfX1RYOo3ik4zwlxdu.woff2
pypillar/static/fonts/6xKydSBYKcSV-LCoeQqfX1RYOo3ik4zwmBduz8A.woff2
pypillar/static/fonts/6xKydSBYKcSV-LCoeQqfX1RYOo3ik4zwmRduz8A.woff2
pypillar-0.0.5.dist-info/LICENSE
pypillar-0.0.5.dist-info/METADATA
pypillar-0.0.5.dist-info/WHEEL
pypillar-0.0.5.dist-info/entry_points.txt
pypillar-0.0.5.dist-info/top_level.txt
pypillar-0.0.5.dist-info/RECORD
