Metadata-Version: 2.1
Name: pypillar
Version: 0.0.5
Summary: Distribute large python execution in task
Home-page: UNKNOWN
Author: Washim Ahmed
Author-email: washim.ahmed@gmail.com
License: MIT license
Platform: UNKNOWN
Classifier: Programming Language :: Python :: 3
Classifier: License :: OSI Approved :: MIT License
Classifier: Operating System :: OS Independent
Requires-Python: >=3
Requires-Dist: Flask
Requires-Dist: Flask-WTF
Requires-Dist: WTForms
Requires-Dist: tinydb
